Workbook

Sheet scraped
A1: author | B1: date | C1: rating | D1: reviews | E1: photos_count | G1: sentiment
A2: Katie Cameron | B2: a month ago | C2: 5 | D2: Beautiful park to wander round. We were there at the wrong time of year to see all the flowers in bloom, but i imagine it would be 10x more beautiful to see. The greener and lake was lovely, with some nice statues and water features. Free to enter with free toilets and parking. | G2: =IF(C2>=4,"positive", IF(C2>=3,"neutral","negative")) -> positive
A3: StoryMiles | B3: 2 months ago | C3: 5 | D3: Chiang Mai Chaloem Phrakiat Park is a peaceful green spot in the city that’s perfect for a morning walk or light exercise. The park has a nice layout with pathways surrounded by trees, flowers, and open space where locals and visitors come to relax. The views inside are beautiful, especially in the early morning when the air is fresh and the atmosphere is calm. It’s not a very large park, but it’s well-maintained and provides a quiet break from the busy streets outside. Many people use it for jogging, walking, or stretching, and you’ll often see groups of locals doing exercises. There are benches and shaded areas where you can sit and enjoy the surroundings. Overall, it’s a simple but pleasant park—nothing fancy, yet a very good choice if you’re staying nearby and want to enjoy some greenery, morning activity, or just a peaceful walk in Chiang Mai. | G3: =IF(C3>=4,"positive", IF(C3>=3,"neutral","negative")) -> positive
A4: Anggita Indari | B4: 5 months ago | C4: 5 | D4: Favorite place in the city 💕 esp during winter! The weather was nice back in January. The sky was clear. The grass was green and clean. I often had a picnic here. Definitely worth a visit just to chill and enjoy the evening. | G4: =IF(C4>=4,"positive", IF(C4>=3,"neutral","negative")) -> positive
A5: יהב גונן | B5: 2 months ago | C5: 5 | D5: A lovely, huge, and pleasant park. Suitable for a family outing. We arrived in a season without flowers, but a walk in the nearby lakes was enjoyable and beautiful. Wide and generous lawns. | G5: =IF(C5>=4,"positive", IF(C5>=3,"neutral","negative")) -> positive
A6: Saswat Mishra | B6: 5 months ago | C6: 5 | D6: Went around sunset. Very pretty and expansive park grounds with wonderful lake views, grass meadows and delightful flowers. Great for walks and family outings. Small snack stalls come up around evening and clean toilet facilities are available. | G6: =IF(C6>=4,"positive", IF(C6>=3,"neutral","negative")) -> positive
A7: Yaw Z | B7: 6 months ago | C7: 4 | D7: Great place for photos, walking, and running. Since it's not festival season, there are no decorations or many flower displays—mostly just natural scenery. Still, it's a nice spot to relax and enjoy the view. | G7: =IF(C7>=4,"positive", IF(C7>=3,"neutral","negative")) -> positive
A8: Charat’s Victualio | B8: a year ago | C8: 5 | D8: The park offers a peaceful environment, making it a perfect spot to take a break from the city's hustle and bustle. It's well-maintained, clean, and provides various amenities to enjoy outdoor activities. Highly recommended for those looking for a tranquil spot to unwind or engage in physical activities. | G8: =IF(C8>=4,"positive", IF(C8>=3,"neutral","negative")) -> positive
A9: P. Roy | B9: 9 months ago | C9: 5 | D9: Beautiful park with lots of different gorgeous flowers. Spent the whole day there during the Chiang Mai Flower Festival, with a big street food market right next to it. At noon everything was decorated with amazing light installations. A real highlight if you have the chance to go there during the festival. | G9: =IF(C9>=4,"positive", IF(C9>=3,"neutral","negative")) -> positive
A10: panyaphon phiphatkunarnon | B10: a year ago | C10: 4 | D10: perfect spot for anyone looking to enjoy a peaceful walk surrounded by nature. The park features a variety of well-maintained walking paths that cater to both casual walkers and those seeking a more challenging stroll. Lush greenery, blooming flowers, and shaded areas along the paths create a refreshing and calming atmosphere. As you walk, you’ll be serenaded by the sounds of birds and the rustling of leaves, offering a welcome escape from the city’s hustle and bustle. There are plenty of benches and rest areas for breaks, allowing you to relax and take in the scenic beauty, whether you’re by the trees or near the serene pond or stream that runs through the park. The park is also accessible to everyone, with wheelchair- and stroller-friendly paths ensuring that people of all ages and abilities can enjoy the walk. With its blend of natural beauty, tranquility, and accessible trails, [Park Name] is a delightful place to recharge, reflect, and enjoy a walk in nature. | G10: =IF(C10>=4,"positive", IF(C10>=3,"neutral","negative")) -> positive
A11: Woraphat Choengpanya | B11: 10 months ago | C11: 5 | D11: There is currently a light show that is beautifully organized, featuring a variety of flowers and free admission. There are plenty of photo spots, but parking can be a bit challenging, and the parking area is quite dusty. Visiting in the evening is ideal for taking great photos with twilight lighting, avoiding excessive heat, and enjoying the illuminated lights. | G11: =IF(C11>=4,"positive", IF(C11>=3,"neutral","negative")) -> positive
A12: Trang Đặng | B12: 6 months ago | C12: 5 | D12: A should visited place on the way to Chiang Mai University, around 3-4km more This park has a wide area with grasses A great place for enjoying sunset time Good for family picnic or walking with your pets | G12: =IF(C12>=4,"positive", IF(C12>=3,"neutral","negative")) -> positive
A13: Lisa JJ | B13: 10 months ago | C13: 5 | D13: Trust me, if you are the lucky one to join the New Year’s Eve in Chiangmai, you mustn’t miss here. I remember it’s part of the annual flower festival event or welcoming new year celebrations. This is a park around a lake, you should not miss the sunset view. And for sure not miss the nightlight of the flower ocean. Of course, also don’t forget the Music fountain or water curtain lights show on hourly time from 7-10 pm, with fireworks for ending. Tips: info above all come from last January 2024, plz check out before you go to visit | G13: =IF(C13>=4,"positive", IF(C13>=3,"neutral","negative")) -> positive
... A531: yumi toshizawa | B531: 5 months ago | C531: 4 | D531: I love this place , the flowers , the resevoir . Its the perfect place to spend your time with either your family or a partner . I saw some students here as well and also people doing their exercise | G531: =IF(C531>=4,"positive", IF(C531>=3,"neutral","negative")) -> positive

Sheet clean
A1: review_text | B1: Wordcount | C1: Access & Location | D1: Environment | E1: Facilities | F1: Activities & Events | G1: Service & Management | H1: Value
A2: Beautiful park to wander round. We were there at the wrong time of year to see all the flowers in bloom, but i imagine it would be 10x more beautiful to see. The greener and lake was lovely, with some nice statues and water features. Free to enter with free toilets and parking. | B2: =LEN(A2)-LEN(SUBSTITUTE(A2," ",""))+1 -> 53 | C2: {=SUM((MMULT(ISNUMBER(SEARCH(TRANSPOSE(category!$A$2:$A$11), A2))*1, ROW(category!$A$2:$A$11)^0)>0)*1)} -> 1 | D2: {=SUM((MMULT(ISNUMBER(SEARCH(TRANSPOSE(category!$B$2:$B$25), A2))*1, ROW(category!$B$2:$B$25)^0)>0)*1)} -> 1 | E2: {=SUM((MMULT(ISNUMBER(SEARCH(TRANSPOSE(category!$C$2:$C$4), A2))*1, ROW(category!$C$2:$C$4)^0)>0)*1)} -> 0 | F2: {=SUM((MMULT(ISNUMBER(SEARCH(TRANSPOSE(category!$D$2:$D$10), A2))*1, ROW(category!$D$2:$D$10)^0)>0)*1)} -> 0 | G2: {=SUM((MMULT(ISNUMBER(SEARCH(TRANSPOSE(category!$E$2:$E$8), A2))*1, ROW(category!$E$2:$E$8)^0)>0)*1)} -> 0 | H2: {=SUM((MMULT(ISNUMBER(SEARCH(TRANSPOSE(category!$F$2:$F$9), A2))*1, ROW(category!$F$2:$F$9)^0)>0)*1)} -> 0
A3: Chiang Mai Chaloem Phrakiat Park is a peaceful green spot in the city that’s perfect for a morning walk or light exercise. The park has a nice layout with pathways surrounded by trees, flowers, and open space where locals and visitors come to relax. The views inside are beautiful, especially in the early morning when the air is fresh and the atmosphere is calm. It’s not a very large park, but it’s well-maintained and provides a quiet break from the busy streets outside. Many people use it for jogging, walking, or stretching, and you’ll often see groups of locals doing exercises. There are benches and shaded areas where you can sit and enjoy the surroundings. Overall, it’s a simple but pleasant park—nothing fancy, yet a very good choice if you’re staying nearby and want to enjoy some greenery, morning activity, or just a peaceful walk in Chiang Mai. | B3: =LEN(A3)-LEN(SUBSTITUTE(A3," ",""))+1 -> 148 | C3: {=SUM((MMULT(ISNUMBER(SEARCH(TRANSPOSE(category!$A$2:$A$11), A3))*1, ROW(category!$A$2:$A$11)^0)>0)*1)} -> 1 | D3: {=SUM((MMULT(ISNUMBER(SEARCH(TRANSPOSE(category!$B$2:$B$25), A3))*1, ROW(category!$B$2:$B$25)^0)>0)*1)} -> 1 | E3: {=SUM((MMULT(ISNUMBER(SEARCH(TRANSPOSE(category!$C$2:$C$4), A3))*1, ROW(category!$C$2:$C$4)^0)>0)*1)} -> 0 | F3: {=SUM((MMULT(ISNUMBER(SEARCH(TRANSPOSE(category!$D$2:$D$10), A3))*1, ROW(category!$D$2:$D$10)^0)>0)*1)} -> 1 | G3: {=SUM((MMULT(ISNUMBER(SEARCH(TRANSPOSE(category!$E$2:$E$8), A3))*1, ROW(category!$E$2:$E$8)^0)>0)*1)} -> 0 | H3: {=SUM((MMULT(ISNUMBER(SEARCH(TRANSPOSE(category!$F$2:$F$9), A3))*1, ROW(category!$F$2:$F$9)^0)>0)*1)} -> 0
A4: Favorite place in the city 💕 esp during winter! The weather was nice back in January. The sky was clear. The grass was green and clean. I often had a picnic here. Definitely worth a visit just to chill and enjoy the evening. | B4: =LEN(A4)-LEN(SUBSTITUTE(A4," ",""))+1 -> 43 | C4: {=SUM((MMULT(ISNUMBER(SEARCH(TRANSPOSE(category!$A$2:$A$11), A4))*1, ROW(category!$A$2:$A$11)^0)>0)*1)} -> 0 | D4: {=SUM((MMULT(ISNUMBER(SEARCH(TRANSPOSE(category!$B$2:$B$25), A4))*1, ROW(category!$B$2:$B$25)^0)>0)*1)} -> 1 | E4: {=SUM((MMULT(ISNUMBER(SEARCH(TRANSPOSE(category!$C$2:$C$4), A4))*1, ROW(category!$C$2:$C$4)^0)>0)*1)} -> 0 | F4: {=SUM((MMULT(ISNUMBER(SEARCH(TRANSPOSE(category!$D$2:$D$10), A4))*1, ROW(category!$D$2:$D$10)^0)>0)*1)} -> 0 | G4: {=SUM((MMULT(ISNUMBER(SEARCH(TRANSPOSE(category!$E$2:$E$8), A4))*1, ROW(category!$E$2:$E$8)^0)>0)*1)} -> 0 | H4: {=SUM((MMULT(ISNUMBER(SEARCH(TRANSPOSE(category!$F$2:$F$9), A4))*1, ROW(category!$F$2:$F$9)^0)>0)*1)} -> 1
A5: A lovely, huge, and pleasant park. Suitable for a family outing. We arrived in a season without flowers, but a walk in the nearby lakes was enjoyable and beautiful. Wide and generous lawns. | B5: =LEN(A5)-LEN(SUBSTITUTE(A5," ",""))+1 -> 33 | C5: {=SUM((MMULT(ISNUMBER(SEARCH(TRANSPOSE(category!$A$2:$A$11), A5))*1, ROW(category!$A$2:$A$11)^0)>0)*1)} -> 1 | D5: {=SUM((MMULT(ISNUMBER(SEARCH(TRANSPOSE(category!$B$2:$B$25), A5))*1, ROW(category!$B$2:$B$25)^0)>0)*1)} -> 1 | E5: {=SUM((MMULT(ISNUMBER(SEARCH(TRANSPOSE(category!$C$2:$C$4), A5))*1, ROW(category!$C$2:$C$4)^0)>0)*1)} -> 0 | F5: {=SUM((MMULT(ISNUMBER(SEARCH(TRANSPOSE(category!$D$2:$D$10), A5))*1, ROW(category!$D$2:$D$10)^0)>0)*1)} -> 1 | G5: {=SUM((MMULT(ISNUMBER(SEARCH(TRANSPOSE(category!$E$2:$E$8), A5))*1, ROW(category!$E$2:$E$8)^0)>0)*1)} -> 0 | H5: {=SUM((MMULT(ISNUMBER(SEARCH(TRANSPOSE(category!$F$2:$F$9), A5))*1, ROW(category!$F$2:$F$9)^0)>0)*1)} -> 0
A6: Went around sunset. Very pretty and expansive park grounds with wonderful lake views, grass meadows and delightful flowers. Great for walks and family outings. Small snack stalls come up around evening and clean toilet facilities are available. | B6: =LEN(A6)-LEN(SUBSTITUTE(A6," ",""))+1 -> 37 | C6: {=SUM((MMULT(ISNUMBER(SEARCH(TRANSPOSE(category!$A$2:$A$11), A6))*1, ROW(category!$A$2:$A$11)^0)>0)*1)} -> 1 | D6: {=SUM((MMULT(ISNUMBER(SEARCH(TRANSPOSE(category!$B$2:$B$25), A6))*1, ROW(category!$B$2:$B$25)^0)>0)*1)} -> 1 | E6: {=SUM((MMULT(ISNUMBER(SEARCH(TRANSPOSE(category!$C$2:$C$4), A6))*1, ROW(category!$C$2:$C$4)^0)>0)*1)} -> 0 | F6: {=SUM((MMULT(ISNUMBER(SEARCH(TRANSPOSE(category!$D$2:$D$10), A6))*1, ROW(category!$D$2:$D$10)^0)>0)*1)} -> 1 | G6: {=SUM((MMULT(ISNUMBER(SEARCH(TRANSPOSE(category!$E$2:$E$8), A6))*1, ROW(category!$E$2:$E$8)^0)>0)*1)} -> 0 | H6: {=SUM((MMULT(ISNUMBER(SEARCH(TRANSPOSE(category!$F$2:$F$9), A6))*1, ROW(category!$F$2:$F$9)^0)>0)*1)} -> 0
A7: Great place for photos, walking, and running. Since it's not festival season, there are no decorations or many flower displays—mostly just natural scenery. Still, it's a nice spot to relax and enjoy the view. | B7: =LEN(A7)-LEN(SUBSTITUTE(A7," ",""))+1 -> 34 | C7: {=SUM((MMULT(ISNUMBER(SEARCH(TRANSPOSE(category!$A$2:$A$11), A7))*1, ROW(category!$A$2:$A$11)^0)>0)*1)} -> 1 | D7: {=SUM((MMULT(ISNUMBER(SEARCH(TRANSPOSE(category!$B$2:$B$25), A7))*1, ROW(category!$B$2:$B$25)^0)>0)*1)} -> 1 | E7: {=SUM((MMULT(ISNUMBER(SEARCH(TRANSPOSE(category!$C$2:$C$4), A7))*1, ROW(category!$C$2:$C$4)^0)>0)*1)} -> 0 | F7: {=SUM((MMULT(ISNUMBER(SEARCH(TRANSPOSE(category!$D$2:$D$10), A7))*1, ROW(category!$D$2:$D$10)^0)>0)*1)} -> 1 | G7: {=SUM((MMULT(ISNUMBER(SEARCH(TRANSPOSE(category!$E$2:$E$8), A7))*1, ROW(category!$E$2:$E$8)^0)>0)*1)} -> 0 | H7: {=SUM((MMULT(ISNUMBER(SEARCH(TRANSPOSE(category!$F$2:$F$9), A7))*1, ROW(category!$F$2:$F$9)^0)>0)*1)} -> 0
A8: The park offers a peaceful environment, making it a perfect spot to take a break from the city's hustle and bustle. It's well-maintained, clean, and provides various amenities to enjoy outdoor activities. Highly recommended for those looking for a tranquil spot to unwind or engage in physical activities. | B8: =LEN(A8)-LEN(SUBSTITUTE(A8," ",""))+1 -> 48 | C8: {=SUM((MMULT(ISNUMBER(SEARCH(TRANSPOSE(category!$A$2:$A$11), A8))*1, ROW(category!$A$2:$A$11)^0)>0)*1)} -> 0 | D8: {=SUM((MMULT(ISNUMBER(SEARCH(TRANSPOSE(category!$B$2:$B$25), A8))*1, ROW(category!$B$2:$B$25)^0)>0)*1)} -> 1 | E8: {=SUM((MMULT(ISNUMBER(SEARCH(TRANSPOSE(category!$C$2:$C$4), A8))*1, ROW(category!$C$2:$C$4)^0)>0)*1)} -> 1 | F8: {=SUM((MMULT(ISNUMBER(SEARCH(TRANSPOSE(category!$D$2:$D$10), A8))*1, ROW(category!$D$2:$D$10)^0)>0)*1)} -> 0 | G8: {=SUM((MMULT(ISNUMBER(SEARCH(TRANSPOSE(category!$E$2:$E$8), A8))*1, ROW(category!$E$2:$E$8)^0)>0)*1)} -> 0 | H8: {=SUM((MMULT(ISNUMBER(SEARCH(TRANSPOSE(category!$F$2:$F$9), A8))*1, ROW(category!$F$2:$F$9)^0)>0)*1)} -> 0
A9: Beautiful park with lots of different gorgeous flowers. Spent the whole day there during the Chiang Mai Flower Festival, with a big street food market right next to it. At noon everything was decorated with amazing light installations. A real highlight if you have the chance to go there during the festival. | B9: =LEN(A9)-LEN(SUBSTITUTE(A9," ",""))+1 -> 52 | C9: {=SUM((MMULT(ISNUMBER(SEARCH(TRANSPOSE(category!$A$2:$A$11), A9))*1, ROW(category!$A$2:$A$11)^0)>0)*1)} -> 1 | D9: {=SUM((MMULT(ISNUMBER(SEARCH(TRANSPOSE(category!$B$2:$B$25), A9))*1, ROW(category!$B$2:$B$25)^0)>0)*1)} -> 1 | E9: {=SUM((MMULT(ISNUMBER(SEARCH(TRANSPOSE(category!$C$2:$C$4), A9))*1, ROW(category!$C$2:$C$4)^0)>0)*1)} -> 0 | F9: {=SUM((MMULT(ISNUMBER(SEARCH(TRANSPOSE(category!$D$2:$D$10), A9))*1, ROW(category!$D$2:$D$10)^0)>0)*1)} -> 1 | G9: {=SUM((MMULT(ISNUMBER(SEARCH(TRANSPOSE(category!$E$2:$E$8), A9))*1, ROW(category!$E$2:$E$8)^0)>0)*1)} -> 0 | H9: {=SUM((MMULT(ISNUMBER(SEARCH(TRANSPOSE(category!$F$2:$F$9), A9))*1, ROW(category!$F$2:$F$9)^0)>0)*1)} -> 0
A10: perfect spot for anyone looking to enjoy a peaceful walk surrounded by nature. The park features a variety of well-maintained walking paths that cater to both casual walkers and those seeking a more challenging stroll. Lush greenery, blooming flowers, and shaded areas along the paths create a refreshing and calming atmosphere. As you walk, you’ll be serenaded by the sounds of birds and the rustling of leaves, offering a welcome escape from the city’s hustle and bustle. There are plenty of benches and rest areas for breaks, allowing you to relax and take in the scenic beauty, whether you’re by the trees or near the serene pond or stream that runs through the park. The park is also accessible to everyone, with wheelchair- and stroller-friendly paths ensuring that people of all ages and abilities can enjoy the walk. With its blend of natural beauty, tranquility, and accessible trails, [Park Name] is a delightful place to recharge, reflect, and enjoy a walk in nature. | B10: =LEN(A10)-LEN(SUBSTITUTE(A10," ",""))+1 -> 163 | C10: {=SUM((MMULT(ISNUMBER(SEARCH(TRANSPOSE(category!$A$2:$A$11), A10))*1, ROW(category!$A$2:$A$11)^0)>0)*1)} -> 1 | D10: {=SUM((MMULT(ISNUMBER(SEARCH(TRANSPOSE(category!$B$2:$B$25), A10))*1, ROW(category!$B$2:$B$25)^0)>0)*1)} -> 1 | E10: {=SUM((MMULT(ISNUMBER(SEARCH(TRANSPOSE(category!$C$2:$C$4), A10))*1, ROW(category!$C$2:$C$4)^0)>0)*1)} -> 0 | F10: {=SUM((MMULT(ISNUMBER(SEARCH(TRANSPOSE(category!$D$2:$D$10), A10))*1, ROW(category!$D$2:$D$10)^0)>0)*1)} -> 1 | G10: {=SUM((MMULT(ISNUMBER(SEARCH(TRANSPOSE(category!$E$2:$E$8), A10))*1, ROW(category!$E$2:$E$8)^0)>0)*1)} -> 1 | H10: {=SUM((MMULT(ISNUMBER(SEARCH(TRANSPOSE(category!$F$2:$F$9), A10))*1, ROW(category!$F$2:$F$9)^0)>0)*1)} -> 0
A11: There is currently a light show that is beautifully organized, featuring a variety of flowers and free admission. There are plenty of photo spots, but parking can be a bit challenging, and the parking area is quite dusty. Visiting in the evening is ideal for taking great photos with twilight lighting, avoiding excessive heat, and enjoying the illuminated lights. | B11: =LEN(A11)-LEN(SUBSTITUTE(A11," ",""))+1 -> 59 | C11: {=SUM((MMULT(ISNUMBER(SEARCH(TRANSPOSE(category!$A$2:$A$11), A11))*1, ROW(category!$A$2:$A$11)^0)>0)*1)} -> 1 | D11: {=SUM((MMULT(ISNUMBER(SEARCH(TRANSPOSE(category!$B$2:$B$25), A11))*1, ROW(category!$B$2:$B$25)^0)>0)*1)} -> 1 | E11: {=SUM((MMULT(ISNUMBER(SEARCH(TRANSPOSE(category!$C$2:$C$4), A11))*1, ROW(category!$C$2:$C$4)^0)>0)*1)} -> 0 | F11: {=SUM((MMULT(ISNUMBER(SEARCH(TRANSPOSE(category!$D$2:$D$10), A11))*1, ROW(category!$D$2:$D$10)^0)>0)*1)} -> 1 | G11: {=SUM((MMULT(ISNUMBER(SEARCH(TRANSPOSE(category!$E$2:$E$8), A11))*1, ROW(category!$E$2:$E$8)^0)>0)*1)} -> 0 | H11: {=SUM((MMULT(ISNUMBER(SEARCH(TRANSPOSE(category!$F$2:$F$9), A11))*1, ROW(category!$F$2:$F$9)^0)>0)*1)} -> 0
A12: A should visited place on the way to Chiang Mai University, around 3-4km more This park has a wide area with grasses A great place for enjoying sunset time Good for family picnic or walking with your pets | B12: =LEN(A12)-LEN(SUBSTITUTE(A12," ",""))+1 -> 38 | C12: {=SUM((MMULT(ISNUMBER(SEARCH(TRANSPOSE(category!$A$2:$A$11), A12))*1, ROW(category!$A$2:$A$11)^0)>0)*1)} -> 1 | D12: {=SUM((MMULT(ISNUMBER(SEARCH(TRANSPOSE(category!$B$2:$B$25), A12))*1, ROW(category!$B$2:$B$25)^0)>0)*1)} -> 1 | E12: {=SUM((MMULT(ISNUMBER(SEARCH(TRANSPOSE(category!$C$2:$C$4), A12))*1, ROW(category!$C$2:$C$4)^0)>0)*1)} -> 0 | F12: {=SUM((MMULT(ISNUMBER(SEARCH(TRANSPOSE(category!$D$2:$D$10), A12))*1, ROW(category!$D$2:$D$10)^0)>0)*1)} -> 1 | G12: {=SUM((MMULT(ISNUMBER(SEARCH(TRANSPOSE(category!$E$2:$E$8), A12))*1, ROW(category!$E$2:$E$8)^0)>0)*1)} -> 0 | H12: {=SUM((MMULT(ISNUMBER(SEARCH(TRANSPOSE(category!$F$2:$F$9), A12))*1, ROW(category!$F$2:$F$9)^0)>0)*1)} -> 0
A13: Trust me, if you are the lucky one to join the New Year’s Eve in Chiangmai, you mustn’t miss here. I remember it’s part of the annual flower festival event or welcoming new year celebrations. This is a park around a lake, you should not miss the sunset view. And for sure not miss the nightlight of the flower ocean. Of course, also don’t forget the Music fountain or water curtain lights show on hourly time from 7-10 pm, with fireworks for ending. Tips: info above all come from last January 2024, plz check out before you go to visit | B13: =LEN(A13)-LEN(SUBSTITUTE(A13," ",""))+1 -> 100 | C13: {=SUM((MMULT(ISNUMBER(SEARCH(TRANSPOSE(category!$A$2:$A$11), A13))*1, ROW(category!$A$2:$A$11)^0)>0)*1)} -> 0 | D13: {=SUM((MMULT(ISNUMBER(SEARCH(TRANSPOSE(category!$B$2:$B$25), A13))*1, ROW(category!$B$2:$B$25)^0)>0)*1)} -> 1 | E13: {=SUM((MMULT(ISNUMBER(SEARCH(TRANSPOSE(category!$C$2:$C$4), A13))*1, ROW(category!$C$2:$C$4)^0)>0)*1)} -> 0 | F13: {=SUM((MMULT(ISNUMBER(SEARCH(TRANSPOSE(category!$D$2:$D$10), A13))*1, ROW(category!$D$2:$D$10)^0)>0)*1)} -> 1 | G13: {=SUM((MMULT(ISNUMBER(SEARCH(TRANSPOSE(category!$E$2:$E$8), A13))*1, ROW(category!$E$2:$E$8)^0)>0)*1)} -> 1 | H13: {=SUM((MMULT(ISNUMBER(SEARCH(TRANSPOSE(category!$F$2:$F$9), A13))*1, ROW(category!$F$2:$F$9)^0)>0)*1)} -> 0
... A531: I love this place , the flowers , the resevoir . Its the perfect place to spend your time with either your family or a partner . I saw some students here as well and also people doing their exercise | B531: =LEN(A531)-LEN(SUBSTITUTE(A531," ",""))+1 -> 40 | C531: {=SUM((MMULT(ISNUMBER(SEARCH(TRANSPOSE(category!$A$2:$A$11), A531))*1, ROW(category!$A$2:$A$11)^0)>0)*1)} -> 0 | D531: {=SUM((MMULT(ISNUMBER(SEARCH(TRANSPOSE(category!$B$2:$B$25), A531))*1, ROW(category!$B$2:$B$25)^0)>0)*1)} -> 1 | E531: {=SUM((MMULT(ISNUMBER(SEARCH(TRANSPOSE(category!$C$2:$C$4), A531))*1, ROW(category!$C$2:$C$4)^0)>0)*1)} -> 0 | F531: {=SUM((MMULT(ISNUMBER(SEARCH(TRANSPOSE(category!$D$2:$D$10), A531))*1, ROW(category!$D$2:$D$10)^0)>0)*1)} -> 1 | G531: {=SUM((MMULT(ISNUMBER(SEARCH(TRANSPOSE(category!$E$2:$E$8), A531))*1, ROW(category!$E$2:$E$8)^0)>0)*1)} -> 0 | H531: {=SUM((MMULT(ISNUMBER(SEARCH(TRANSPOSE(category!$F$2:$F$9), A531))*1, ROW(category!$F$2:$F$9)^0)>0)*1)} -> 0
B533: total | C533: =SUM(C2:C531) -> 114 | D533: =SUM(D2:D531) -> 476 | E533: =SUM(E2:E531) -> 32 | F533: =SUM(F2:F531) -> 223 | G533: =SUM(G2:G531) -> 21 | H533: =SUM(H2:H531) -> 43

Sheet category
A1: Access & Location | B1: Environment | C1: Facilities | D1: Activities & Events | E1: Service & Management | F1: Value
A2: parking | B2: beautiful | C2: amenities | D2: walk | E2: staff | F2: value
A3: walking | B3: flower | C3: bathroom | D3: festival | E3: service | F3: worth
A4: convenient | B4: park | C4: spacious | D4: show | E4: welcoming | F4: price
A5: near | B5: garden | D5: shopping | E5: friendly | F5: cost
A6: street | B6: decor | D6: Food | E6: management | F6: affordable
A7: center | B7: clean | D7: activities | E7: team | F7: cheap
A8: mall | B8: cleanliness | D8: exercise | E8: support | F8: expensive
A9: close | B9: tidy | D9: jogging | F9: Charming
A10: location | B10: fresh | D10: music
A11: locals | B11: peaceful
B12: calm
B13: quiet
B14: comfortable
B15: great
B16: good
B17: night
B18: Place
B19: winter
B20: relax
B21: Wide
B22: weather
B23: beauty
... B25: wonderful
